latex_lib/__init__.py
latex_lib/latex_func.py
latex_lib-0.1.0.dist-info/LICENSE
latex_lib-0.1.0.dist-info/METADATA
latex_lib-0.1.0.dist-info/WHEEL
latex_lib-0.1.0.dist-info/top_level.txt
latex_lib-0.1.0.dist-info/RECORD
