Metadata-Version: 2.1
Name: latex-lib
Version: 0.1.0
Summary: Генератор LaTeX таблиц и LaTeX картинок
Home-page: https://github.com/Qeshtir/ITMO_Advanced_Python/hw_2/latex_lib
Author: Igor Makarov
Author-email: realneiro@gmail.com
Classifier: Programming Language :: Python :: 3
Classifier: License :: OSI Approved :: MIT License
Classifier: Operating System :: OS Independent
Requires-Python: >=3.9
License-File: LICENSE
